stads/__init__.py
stads/config.py
stads/evaluation.py
stads/experiments.py
stads/experiments_setup.py
stads/image_processing.py
stads/interpolator.py
stads/microscope.py
stads/monitor.py
stads/random_sampler.py
stads/read_images.py
stads/stads.py
stads/stads_helpers.py
stads/stratified_sampler.py
stads/stratified_sampler_helpers.py
stads/utility_functions.py
stads/video_downloader.py
stads-1.7.0.dist-info/METADATA
stads-1.7.0.dist-info/WHEEL
stads-1.7.0.dist-info/top_level.txt
stads-1.7.0.dist-info/RECORD
