Metadata-Version: 2.4
Name: stads
Version: 1.7.0
Summary: a spatiotemporal statistics-based adaptive sampling algorithm
Home-page: https://github.com/bharadwajakarsh/stads_adaptive_sampler
Author: Akarsh Bharadwaj
Author-email: akarsh_sudheendra.bharadwaj@dfki.de
Classifier: Programming Language :: Python :: 3
Classifier: Operating System :: OS Independent
Requires-Python: >=3.8
Requires-Dist: numpy
Requires-Dist: scikit-image
Requires-Dist: matplotlib
Requires-Dist: scipy
Requires-Dist: joblib
Requires-Dist: numba
Requires-Dist: opencv-python
Requires-Dist: ipywidgets
Requires-Dist: ipython
Requires-Dist: tqdm
Requires-Dist: requests
Dynamic: author
Dynamic: author-email
Dynamic: classifier
Dynamic: home-page
Dynamic: requires-dist
Dynamic: requires-python
Dynamic: summary
